qlmetrics/__init__.py
qlmetrics/bench.py
qlmetrics-0.0.1.dist-info/METADATA
qlmetrics-0.0.1.dist-info/RECORD
qlmetrics-0.0.1.dist-info/WHEEL
qlmetrics-0.0.1.dist-info/top_level.txt
