Metadata-Version: 2.1
Name: qlmetrics
Version: 0.0.1
Summary: Metrics tracker
Home-page: https://github.com/QsonLabs/qlmetrics
Author: Chris O'Connor
Author-email: cdoconno@gmail.com
License: Apache
Platform: UNKNOWN
Classifier: Development Status :: 4 - Beta
Classifier: Framework :: Flake8
Classifier: Framework :: tox
Classifier: License :: OSI Approved :: Apache Software License
Classifier: Operating System :: MacOS
Classifier: Operating System :: Unix
Classifier: Programming Language :: Python :: 2.7
Classifier: Programming Language :: Python :: 3.7
